{"students":[{"id":1,"name":"张中三","gender":0,"age":"18","hobbies":"吃饭、睡觉、打豆豆、lol"},{"id":2,"name":"张大三","gender":0,"age":"18","hobbies":"吃饭、睡觉、打豆豆、lol"},{"id":4,"name":"张三","gender":0,"age":18,"hobbies":"吃饭、睡觉、打豆豆、lol"},{"id":5,"name":"张三","gender":0,"age":18,"hobbies":"吃饭、睡觉、打豆豆、lol"},{"id":6,"name":"张三","gender":0,"age":18,"hobbies":"吃饭、睡觉、打豆豆、lol"},{"name":"1132432","gender":"0","age":"434","hobbies":"444","id":7},{"name":"13123","gender":"0","age":"123123","hobbies":"12312312","id":9},{"name":"我爱你","gender":"0","age":"99","hobbies":"没有","id":10}]}